ecommerce_exporter
