Metadata-Version: 2.1
Name: ecommerce-exporter
Version: 0.0.8
Summary: ecommerce-exporter is a prometheus exporter that export the price of products in e-commerce site as prometheus metrics.
Home-page: https://code.badjware.dev/badjware/ecommerce-exporter
Author: badjware
Author-email: marchambault@badjware.dev
License: UNKNOWN
Platform: any
Requires-Python: >=3.10.0
